kthcloud/__init__.py
kthcloud/_base_client.py
kthcloud/_client.py
kthcloud/_compat.py
kthcloud/_constants.py
kthcloud/_exceptions.py
kthcloud/_files.py
kthcloud/_models.py
kthcloud/_qs.py
kthcloud/_resource.py
kthcloud/_response.py
kthcloud/_streaming.py
kthcloud/_types.py
kthcloud/_version.py
kthcloud/py.typed
kthcloud/_utils/__init__.py
kthcloud/_utils/_logs.py
kthcloud/_utils/_proxy.py
kthcloud/_utils/_streams.py
kthcloud/_utils/_sync.py
kthcloud/_utils/_transform.py
kthcloud/_utils/_typing.py
kthcloud/_utils/_utils.py
kthcloud/lib/.keep
kthcloud/resources/__init__.py
kthcloud/resources/gpu_groups.py
kthcloud/resources/gpu_leases.py
kthcloud/resources/snapshots.py
kthcloud/resources/vm_actions.py
kthcloud/resources/vms/__init__.py
kthcloud/resources/vms/snapshot.py
kthcloud/resources/vms/vms.py
kthcloud/types/__init__.py
kthcloud/types/gpu_group.py
kthcloud/types/gpu_group_list_params.py
kthcloud/types/gpu_group_list_response.py
kthcloud/types/gpu_lease_create_params.py
kthcloud/types/gpu_lease_created.py
kthcloud/types/gpu_lease_deleted.py
kthcloud/types/gpu_lease_list_params.py
kthcloud/types/gpu_lease_list_response.py
kthcloud/types/gpu_lease_read.py
kthcloud/types/gpu_lease_update_params.py
kthcloud/types/gpu_lease_updated.py
kthcloud/types/snapshot_list_params.py
kthcloud/types/snapshot_list_response.py
kthcloud/types/vm_action_create_params.py
kthcloud/types/vm_action_created.py
kthcloud/types/vm_create_params.py
kthcloud/types/vm_created.py
kthcloud/types/vm_deleted.py
kthcloud/types/vm_list_params.py
kthcloud/types/vm_list_response.py
kthcloud/types/vm_read.py
kthcloud/types/vm_snapshot_created.py
kthcloud/types/vm_update_params.py
kthcloud/types/vm_updated.py
kthcloud/types/shared/__init__.py
kthcloud/types/shared/vm_snapshot_read.py
kthcloud/types/vms/__init__.py
kthcloud/types/vms/vm_snapshot_deleted.py
kthcloud-0.6.0a0.dist-info/METADATA
kthcloud-0.6.0a0.dist-info/WHEEL
kthcloud-0.6.0a0.dist-info/licenses/LICENSE
kthcloud-0.6.0a0.dist-info/RECORD
